LICENSE
MANIFEST.in
README.md
setup.py
cd_perf_promotion/__init__.py
cd_perf_promotion/main.py
cd_perf_promotion.egg-info/PKG-INFO
cd_perf_promotion.egg-info/SOURCES.txt
cd_perf_promotion.egg-info/dependency_links.txt
cd_perf_promotion.egg-info/entry_points.txt
cd_perf_promotion.egg-info/requires.txt
cd_perf_promotion.egg-info/top_level.txt
cd_perf_promotion/engines/__init__.py
cd_perf_promotion/engines/argumentengine.py
cd_perf_promotion/engines/comparisonengine.py
cd_perf_promotion/engines/configengine.py
cd_perf_promotion/engines/dataengine.py
cd_perf_promotion/engines/outputengine.py
cd_perf_promotion/modules/__init__.py
cd_perf_promotion/modules/appdynamics.py
cd_perf_promotion/modules/blazemeter.py
cd_perf_promotion/modules/perftools.py
cd_perf_promotion/modules/webpagetest.py
documentation/arguments.md
documentation/bamboo.md
documentation/dictionary.md
documentation/elastic_kibana.md
documentation/elastic_kibana_template.json
documentation/structure.md
documentation/testing.md
documentation/updating.md