Metadata-Version: 1.0
Name: cd-perf-promotion
Version: 1.0.0
Summary: Evaluate and promote builds on a CI/CD platform based on performance
Home-page: https://github.com/CDKGlobal/cd-performance-promotion
Author: Jared Petersen
Author-email: Jared.Petersen@cdk.com
License: MIT
Platform: UNKNOWN
